{
    "id": "enema_administration_orderedResponse_v1",
    "type": "orderedResponse",
    "stem": "The nurse is preparing to administer a large-volume cleansing enema. Place the procedural steps in the correct order.",
    "options": [
        {
            "id": "o1",
            "text": "Position the client in the Left Sims position."
        },
        {
            "id": "o2",
            "text": "Lubricate the tip of the enema tube."
        },
        {
            "id": "o4",
            "text": "Open the clamp and raise the bag to the appropriate height (12-18 inches)."
        },
        {
            "id": "o3",
            "text": "Insert the tube 3-4 inches into the rectum towards the umbilicus."
        },
        {
            "id": "o5",
            "text": "Instruct the client to retain the fluid for as long as possible."
        }
    ],
    "correctOrder": [
        "o1",
        "o2",
        "o3",
        "o4",
        "o5"
    ],
    "pedagogy": {
        "bloomLevel": "apply",
        "cjmmStep": "takeAction",
        "nclexCategory": "Basic Care and Comfort",
        "difficulty": 2,
        "topicTags": [
            "Gastrointestinal",
            "Skills",
            "Safety"
        ]
    },
    "rationale": {
        "correct": "Correct enema administration prevents injury. (1) Left Sims follows the natural curve of the colon. (2) Lubrication prevents mucosal trauma. (3) Proper insertion depth/angle ensures passage into the rectum. (4) Height controls the rate of flow (Gravity). (5) Retaining ensures effectiveness of the cleanse.",
        "incorrect": "Inserting the tube more than 4 inches increases the risk of rectal perforation.",
        "answerBreakdown": [],
        "clinicalPearls": [
            "If the client reports abdominal cramping during administration, lower the bag or stop the flow temporarily for 30 seconds."
        ],
        "questionTrap": {
            "trap": "Bag Height",
            "howToOvercome": "Remember that if a patient cramps, you don't 'stop and remove'—you 'slow it down' by lowering the bag."
        },
        "mnemonic": {
            "title": "L-L-I-H-R",
            "expansion": "Left-Sims, Lubricate, Insert, Height, Retain."
        },
        "reviewUnits": [
            {
                "heading": "Bowel Elimination: Enema Procedures",
                "body": "Nurses monitor for potential vagal response (bradycardia/dizziness). Large volume enemas should be warm (105-110°F).",
                "source": "Fundamentals of Nursing: Elimination"
            }
        ]
    },
    "scoring": {
        "method": "dichotomous",
        "maxPoints": 1
    }
}