{
  "id": "matrixMatch_insulin_management_v2026_21",
  "type": "matrixMatch",
  "matrixType": "multipleChoice",
  "stem": "The nurse is caring for a client with type 1 diabetes mellitus who requires insulin. Based on the provided information, match each insulin type to its expected onset, peak, and duration.",
  "itemContext": {
    "tabs": [
      {
        "id": "sbar",
        "title": "Nurses' Notes",
        "content": "10/26/2026 07:00 - Client reports feeling well this morning. Ate a full breakfast at 06:30. Blood glucose check due before lunch. - Nurse Kim\n\n10/26/2026 11:00 - Pre-lunch blood glucose 250 mg/dL. Client reports no symptoms of hypo- or hyperglycemia. Insulin ordered per sliding scale. - Nurse Kim\n\n10/26/2026 11:15 - 6 units of insulin lispro administered subcutaneously per sliding scale order. Client tolerated injection well. Educated on signs and symptoms of hypoglycemia and hyperglycemia. Encourage client to report any unusual symptoms. - Nurse Kim\n\n10/26/2026 16:00 - Client ate lunch well and reports feeling fine. Blood glucose trending down. Will check pre-dinner blood glucose at 17:00. - Nurse Kim\n\n10/26/2026 17:00 - Pre-dinner blood glucose 140 mg/dL. Client denies any complaints. Continue to monitor. - Nurse Kim\n\n10/26/2026 21:00 - Pre-bedtime blood glucose 110 mg/dL. Client reports feeling well. Administered 12 units of insulin glargine subcutaneously. - Nurse Kim"
      },
      {
        "id": "vitals",
        "title": "Vital Signs",
        "content": "10/26/2026 07:00\nTemperature: 98.6°F (37°C)\nHeart Rate: 72 bpm\nRespiratory Rate: 16 breaths/min\nBlood Pressure: 120/80 mmHg\nSpO2: 98% on room air\n\n10/26/2026 11:00\nTemperature: 98.8°F (37.1°C)\nHeart Rate: 76 bpm\nRespiratory Rate: 16 breaths/min\nBlood Pressure: 124/82 mmHg\nSpO2: 99% on room air\n\n10/26/2026 17:00\nTemperature: 98.7°F (37.1°C)\nHeart Rate: 74 bpm\nRespiratory Rate: 16 breaths/min\nBlood Pressure: 122/81 mmHg\nSpO2: 98% on room air"
      },
      {
        "id": "labs",
        "title": "Lab Results",
        "content": "10/26/2026 11:00\nBlood Glucose: 250 mg/dL\n\n10/26/2026 17:00\nBlood Glucose: 140 mg/dL\n\n10/26/2026 21:00\nBlood Glucose: 110 mg/dL"
      },
      {
        "id": "exam",
        "title": "Physical Exam",
        "content": "10/26/2026 07:00\nGeneral: Alert and oriented x3, well-nourished, no acute distress.\nSkin: Warm, dry, and intact. No lesions or edema.\nCardiovascular: Regular rate and rhythm, no murmurs.\nRespiratory: Clear to auscultation bilaterally.\nAbdomen: Soft, non-tender, normoactive bowel sounds.\nNeurological: Gross motor and sensory intact."
      },
      {
        "id": "orders",
        "title": "Care Plan",
        "content": "Diabetes Management:\n- Monitor blood glucose before meals and at bedtime.\n- Administer insulin as prescribed per sliding scale.\n- Educate client on insulin administration technique.\n- Educate client on signs and symptoms of hypoglycemia and hyperglycemia.\n- Encourage client to report any unusual symptoms.\n- Dietician consult for diabetic meal planning."
      },
      {
        "id": "mar",
        "title": "MAR",
        "content": "Insulin lispro: 6 units SQ at 11:15 on 10/26/2026\nInsulin glargine: 12 units SQ at 21:00 on 10/26/2026"
      }
    ]
  },
  "rows": [
    {
      "id": "r1",
      "text": "Insulin Lispro"
    },
    {
      "id": "r2",
      "text": "Regular Insulin"
    },
    {
      "id": "r3",
      "text": "NPH Insulin"
    },
    {
      "id": "r4",
      "text": "Insulin Glargine"
    }
  ],
  "columns": [
    {
      "id": "c1",
      "text": "Onset: 5-15 min; Peak: 1-2 hr; Duration: 3-5 hr"
    },
    {
      "id": "c2",
      "text": "Onset: 30 min; Peak: 2-4 hr; Duration: 5-8 hr"
    },
    {
      "id": "c3",
      "text": "Onset: 1-2 hr; Peak: 4-12 hr; Duration: 12-18 hr"
    },
    {
      "id": "c4",
      "text": "Onset: 1-2 hr; Peak: None; Duration: 24 hr"
    }
  ],
  "correctAnswers": {
    "r1": [
      "c1"
    ],
    "r2": [
      "c2"
    ],
    "r3": [
      "c3"
    ],
    "r4": [
      "c4"
    ]
  },
  "pedagogy": {
    "bloomLevel": "analyze",
    "cjmmStep": "analyzeCues",
    "nclexCategory": "Physiological Adaptation",
    "difficulty": 4,
    "topicTags": [
      "Insulin Management",
      "Pharmacology",
      "Diabetes Mellitus"
    ]
  },
  "rationale": {
    "correct": "The correct matches are:\n- Insulin Lispro: Onset 5-15 min; Peak 1-2 hr; Duration 3-5 hr.\n- Regular Insulin: Onset 30 min; Peak 2-4 hr; Duration 5-8 hr.\n- NPH Insulin: Onset 1-2 hr; Peak 4-12 hr; Duration 12-18 hr.\n- Insulin Glargine: Onset 1-2 hr; Peak None; Duration 24 hr.",
    "incorrect": "Incorrect selections indicate a misunderstanding of the onset, peak, and duration of different types of insulin. This can lead to inappropriate insulin administration and potential complications such as hypoglycemia or hyperglycemia.",
    "answerBreakdown": [
      {
        "id": "r1",
        "text": "Insulin Lispro",
        "rationale": "Insulin lispro is a rapid-acting insulin analog with an onset of 5-15 minutes, a peak of 1-2 hours, and a duration of 3-5 hours. It is often used for bolus injections before meals to cover carbohydrate intake."
      },
      {
        "id": "r2",
        "text": "Regular Insulin",
        "rationale": "Regular insulin is a short-acting insulin with an onset of 30 minutes, a peak of 2-4 hours, and a duration of 5-8 hours. It is typically administered 30 minutes before meals."
      },
      {
        "id": "r3",
        "text": "NPH Insulin",
        "rationale": "NPH insulin is an intermediate-acting insulin with an onset of 1-2 hours, a peak of 4-12 hours, and a duration of 12-18 hours. It is often used as a basal insulin to provide coverage between meals and overnight."
      },
      {
        "id": "r4",
        "text": "Insulin Glargine",
        "rationale": "Insulin glargine is a long-acting insulin analog with an onset of 1-2 hours, no pronounced peak, and a duration of 24 hours. It provides a consistent level of insulin coverage over 24 hours and is used as a basal insulin."
      }
    ],
    "clinicalPearls": [
      "Understanding the onset, peak, and duration of different insulin types is crucial for preventing hypoglycemia and hyperglycemia.",
      "Rapid-acting insulins are used to cover mealtime carbohydrate intake, while long-acting insulins provide basal coverage.",
      "Factors such as injection site, individual metabolism, and activity level can influence insulin absorption and action."
    ],
    "questionTrap": {
      "trap": "Confusing the peak times of rapid-acting and short-acting insulins is a common mistake.",
      "howToOvercome": "Focus on the onset time to differentiate between rapid-acting and short-acting insulins. Rapid-acting insulins have a very quick onset (5-15 minutes), while short-acting insulins take about 30 minutes to start working."
    },
    "mnemonic": {
      "title": "RRapid acting insulin",
      "expansion": "Lispro (Humalog) and Aspart (Novolog) act RAPIDLY at mealtime."
    }
  },
  "scoring": {
    "method": "polytomous",
    "maxPoints": 4
  },
  "sentinelStatus": "healed_v2026_v8"
}