{
    "id": "abg_interpretation_dragAndDropCloze_v1",
    "type": "dragAndDropCloze",
    "stem": "Determine the acid-base state and the most likely clinical cause for a client with the following ABG results: pH 7.28, PaCO2 55, HCO3 26.",
    "template": "The client is experiencing {{acidBaseState}}, which is likely caused by {{clinicalCause}}.",
    "options": [
        "Respiratory Acidosis",
        "Respiratory Alkalosis",
        "Metabolic Acidosis",
        "Metabolic Alkalosis",
        "Chronic Obstructive Pulmonary Disease (COPD)",
        "Diabetic Ketoacidosis (DKA)",
        "Over-ventilation on a mechanical ventilator",
        "Excessive use of antacids"
    ],
    "blanks": [
        {
            "id": "acidBaseState",
            "correctOption": "Respiratory Acidosis"
        },
        {
            "id": "clinicalCause",
            "correctOption": "Chronic Obstructive Pulmonary Disease (COPD)"
        }
    ],
    "pedagogy": {
        "bloomLevel": "analyze",
        "cjmmStep": "analyzeCues",
        "nclexCategory": "Physiological Adaptation",
        "difficulty": 4,
        "topicTags": [
            "ABGs",
            "Respiratory",
            "COPD"
        ]
    },
    "rationale": {
        "correct": "pH 7.28 (<7.35) = acidosis. PaCO2 55 (>45) = respiratory. HCO3 26 (normal range 22-26) = uncompensated. Respiratory acidosis is caused by hypoventilation, which occurs in COPD due to air trapping and CO2 retention.",
        "incorrect": "DKA causes metabolic acidosis (low pH, low HCO3). Over-ventilation causes respiratory alkalosis (high pH, low CO2). Antacids cause metabolic alkalosis (high pH, high HCO3).",
        "clinicalPearls": [
            "ROME: Respiratory Opposite, Metabolic Equal."
        ],
        "questionTrap": {
            "trap": "Assuming compensation",
            "howToOvercome": "Check the HCO3 first. If it is within 22-26, the body has not yet compensated for a respiratory issue."
        },
        "reviewUnits": [
            {
                "heading": "Acid-Base Fundamentals",
                "body": "Nurses must interpret pH, then CO2 to identify respiratory causes. If the pH and CO2 move in opposite directions, the problem is respiratory.",
                "source": "NCSBN ABG Interpretation Series"
            }
        ],
        "answerBreakdown": [
            {
                "label": "Blank 1",
                "content": "The selection of \"Respiratory Acidosis\" correctly completes the clinical hypothesis based on assessment cues.",
                "isCorrect": true
            },
            {
                "label": "Blank 2",
                "content": "The selection of \"Chronic Obstructive Pulmonary Disease (COPD)\" correctly completes the clinical hypothesis based on assessment cues.",
                "isCorrect": true
            }
        ],
        "mnemonic": {
            "title": "P-R-I-M-E",
            "expansion": "Priority, Research, Intervention, Monitor, Evidence-based"
        }
    },
    "scoring": {
        "method": "polytomous",
        "maxPoints": 2
    }
}