{
    "id": "New-v26-4a7b8c9d-e2f0-41a3-b456-789012345678",
    "type": "selectAll",
    "stem": "The nurse reviews the client's electronic health record. Based on the provided data, which actions should the nurse take immediately? Select all that apply.",
    "options": [
        {
            "id": "option1",
            "text": "Administer oxygen via a non-rebreather mask."
        },
        {
            "id": "option2",
            "text": "Initiate a rapid intravenous fluid bolus."
        },
        {
            "id": "option3",
            "text": "Notify the healthcare provider of the client's status."
        },
        {
            "id": "option4",
            "text": "Reposition the client to a semi-Fowler's position."
        },
        {
            "id": "option5",
            "text": "Place the client on continuous cardiac monitoring."
        },
        {
            "id": "option6",
            "text": "Administer the PRN dose of hydromorphone for pain."
        },
        {
            "id": "option7",
            "text": "Encourage the use of an incentive spirometer."
        }
    ],
    "correctOptionIds": [
        "option1",
        "option2",
        "option3",
        "option4",
        "option5"
    ],
    "itemContext": {
        "patient": {
            "age": "58",
            "sex": "Male",
            "pronouns": "he/him",
            "allergies": [
                "Penicillin"
            ]
        },
        "tabs": [
            {
                "id": "clinical_feed",
                "title": "Clinical Feed",
                "content": "Admission Note (Day 1, 14:00): Client admitted from ED with severe epigastric pain radiating to the back, nausea, and vomiting. History of chronic alcohol use. Diagnosed with acute pancreatitis. Initiated on IV fluids, NPO status, and IV pain management. \n\nProgress Note (Day 3, 06:30):\nS: Client reports a sudden increase in epigastric pain to 9/10, describing it as 'stabbing'. States he feels 'dizzy' and 'can't catch his breath'.\nB: 58-year-old male with alcohol-induced acute pancreatitis. Has required frequent PRN hydromorphone. Client lives alone in a rural area, which may pose a barrier to consistent follow-up care post-discharge.\nA: At 06:15, client is acutely distressed, diaphoretic, and newly confused. Vitals trending towards shock: BP 90/50 mmHg (MAP 63), HR 125 bpm, RR 28/min, SpO₂ 91% on 2L NC. Abdomen is rigid and distended with hypoactive bowel sounds. Urine output is <30 mL/hr for the past 4 hours. Labs indicate hemoconcentration and acute kidney injury.\nR: Recommend immediate intervention for impending hypovolemic shock and respiratory distress. Initiate fluid bolus, increase oxygen support, and provide urgent provider notification for potential ICU transfer."
            },
            {
                "id": "vitals_telemetry",
                "title": "Vitals & Telemetry",
                "content": "<table><thead><tr><th>Time</th><th>BP (mmHg)</th><th>MAP (mmHg)</th><th>HR (bpm)</th><th>RR (/min)</th><th>SpO₂</th><th>Temp °F (°C)</th></tr></thead><tbody><tr><td>02:00</td><td>110/70</td><td>83</td><td>98</td><td>20</td><td>96% on 2L NC</td><td>99.0 (37.2)</td></tr><tr><td>04:00</td><td>100/60</td><td>73</td><td>105</td><td>24</td><td>94% on 2L NC</td><td>99.5 (37.5)</td></tr><tr><td>06:15</td><td>90/50</td><td>63</td><td>125</td><td>28</td><td>91% on 2L NC</td><td>100.0 (37.8)</td></tr></tbody></table>"
            },
            {
                "id": "lab_diagnostics",
                "title": "Lab Diagnostics",
                "content": "<table><thead><tr><th>Lab</th><th>Result</th><th>Unit</th><th>Reference Range</th><th>Status</th></tr></thead><tbody><tr><td>Amylase</td><td>1500</td><td>U/L</td><td>25-125</td><td>High</td></tr><tr><td>Lipase</td><td>2000</td><td>U/L</td><td>10-150</td><td>High</td></tr><tr><td>Sodium</td><td>130</td><td>mEq/L</td><td>135-145</td><td>Low</td></tr><tr><td>Potassium</td><td>3.2</td><td>mEq/L</td><td>3.5-5.0</td><td>Low</td></tr><tr><td>Calcium, Total</td><td>7.9</td><td>mg/dL</td><td>8.5-10.2</td><td>Low</td></tr><tr><td>Glucose</td><td>185</td><td>mg/dL</td><td>70-110</td><td>High</td></tr><tr><td>BUN</td><td>30</td><td>mg/dL</td><td>10-20</td><td>High</td></tr><tr><td>Creatinine</td><td>1.8</td><td>mg/dL</td><td>0.6-1.2</td><td>High</td></tr><tr><td>Hematocrit</td><td>52</td><td>%</td><td>38-50 (Male)</td><td>High</td></tr></tbody></table>"
            },
            {
                "id": "physical_exam",
                "title": "Physical Exam",
                "content": "(06:15) \nNeurological: Newly confused and agitated, not oriented to time or place.\nCardiovascular: Tachycardic with regular rhythm. Pulses +1 peripherally. Skin is cool and diaphoretic.\nRespiratory: Tachypneic with shallow respirations. Lungs with crackles in bilateral bases.\nGI: Abdomen rigid, distended, and tender to palpation in all quadrants. Bowel sounds hypoactive."
            },
            {
                "id": "radiology",
                "title": "Radiology",
                "content": "CT Abdomen/Pelvis with Contrast (Day 1)\n\nFINDINGS: Diffuse enlargement and inflammation of the pancreas with peripancreatic fat stranding and fluid collections consistent with acute interstitial edematous pancreatitis. No evidence of pancreatic necrosis. Small bilateral pleural effusions noted.\n\nIMPRESSION: Findings are consistent with acute pancreatitis."
            },
            {
                "id": "care_plan",
                "title": "Care Plan (Orders)",
                "content": "<table><thead><tr><th>Order Date/Time</th><th>Action</th><th>Frequency/Status</th></tr></thead><tbody><tr><td>Day 1, 14:00</td><td>NPO</td><td>Standing</td></tr><tr><td>Day 1, 14:00</td><td>Lactated Ringers at 100 mL/hr</td><td>Continuous</td></tr><tr><td>Day 1, 14:00</td><td>Bed rest with bathroom privileges</td><td>Standing</td></tr><tr><td>Day 1, 14:00</td><td>Hydromorphone 2 mg IV</td><td>q4h PRN severe pain</td></tr><tr><td>Day 1, 14:00</td><td>Ondansetron 4 mg IV</td><td>q6h PRN nausea</td></tr><tr><td>Day 1, 14:00</td><td>Pantoprazole 40 mg IV</td><td>Daily</td></tr></tbody></table>"
            },
            {
                "id": "mar_console",
                "title": "MAR Console",
                "content": "<table><thead><tr><th>Medication</th><th>Dose</th><th>Route</th><th>Frequency</th><th>Last Administered</th></tr></thead><tbody><tr><td>Hydromorphone</td><td>2 mg</td><td>IV</td><td>q4h PRN pain</td><td>05:30</td></tr><tr><td>Ondansetron</td><td>4 mg</td><td>IV</td><td>q6h PRN nausea</td><td>02:00</td></tr><tr><td>Lactated Ringers</td><td>100 mL/hr</td><td>IV</td><td>Continuous</td><td>Ongoing</td></tr><tr><td>Pantoprazole</td><td>40 mg</td><td>IV</td><td>Daily</td><td>Day 3, 08:00 (Scheduled)</td></tr></tbody></table>"
            }
        ]
    },
    "rationale": {
        "correct": "The client is exhibiting signs of severe acute pancreatitis progressing to systemic inflammatory response syndrome (SIRS), hypovolemic shock, and acute respiratory distress syndrome (ARDS). Immediate priorities are to correct hypoxemia and hypotension (Circulation, Breathing) and escalate care. This requires increasing oxygen delivery, aggressive fluid resuscitation, placing the client in a position to optimize breathing, initiating cardiac monitoring due to instability and electrolyte imbalances, and notifying the provider.",
        "incorrect": "Administering more opioids is contraindicated due to the client's hypotension and respiratory compromise. Encouraging incentive spirometry is a lower priority than correcting acute hypoxemia and is likely not feasible given the client's altered mental status and respiratory distress.",
        "answerBreakdown": [
            {
                "optionId": "option1",
                "content": "Correct. The SpO₂ of 91% on 2L NC indicates significant hypoxemia. Pancreatic inflammation can lead to ARDS and pleural effusions. A non-rebreather mask delivers a higher FiO₂, which is essential to correct tissue hypoxia and prevent further organ damage."
            },
            {
                "optionId": "option2",
                "content": "Correct. The client's hypotension (BP 90/50), tachycardia (HR 125), elevated hematocrit (52%), and rising creatinine (1.8) are hallmark signs of third-spacing and hypovolemic shock. A rapid fluid bolus is the priority intervention to restore intravascular volume and perfuse vital organs."
            },
            {
                "optionId": "option3",
                "content": "Correct. The client's rapid clinical deterioration with signs of multi-organ dysfunction (respiratory, cardiovascular, renal, neurological) is a medical emergency. The nurse must escalate care immediately to the provider to obtain orders for ICU transfer, vasopressors, or other advanced therapies."
            },
            {
                "optionId": "option4",
                "content": "Correct. Abdominal distention from ileus and ascites can splint the diaphragm, reducing lung expansion and worsening atelectasis. The semi-Fowler's position uses gravity to lower the diaphragm, increasing thoracic volume and easing the work of breathing."
            },
            {
                "optionId": "option5",
                "content": "Correct. The client has hypokalemia (3.2 mEq/L) and hypocalcemia (7.9 mg/dL), both of which increase the risk for cardiac dysrhythmias. Combined with the severe physiologic stress and tachycardia, continuous cardiac monitoring is a critical safety measure to detect life-threatening arrhythmias."
            },
            {
                "optionId": "option6",
                "content": "Incorrect. While the client is in pain, administering more opioids is unsafe. Hydromorphone can cause vasodilation and respiratory depression, which would worsen the client's existing hypotension and hypoxemia. Hemodynamic stabilization is the priority over pain management in this acute phase."
            },
            {
                "optionId": "option7",
                "content": "Incorrect. Incentive spirometry is important for preventing atelectasis but is not a priority during an acute decompensation. The client's altered mental status and severe respiratory distress make this intervention inappropriate and ineffective until the underlying hypoxemia is addressed."
            }
        ],
        "clinicalPearls": [
            "In severe acute pancreatitis, aggressive IV fluid resuscitation (e.g., 250-500 mL/hr of isotonic crystalloid) in the first 12-24 hours is a cornerstone of therapy to prevent pancreatic necrosis and organ failure.",
            "Hypocalcemia in pancreatitis occurs due to saponification, where calcium binds to free fatty acids in areas of fat necrosis. Monitor for Chvostek's and Trousseau's signs.",
            "Pulmonary complications, including atelectasis, pleural effusions, and ARDS, are the leading cause of early mortality in acute pancreatitis. Maintain a high index of suspicion for respiratory compromise."
        ],
        "questionTrap": "The primary trap is focusing on the client's report of severe pain and selecting the PRN opioid as a priority. While pain is a major symptom, the ABCs (Airway, Breathing, Circulation) must take precedence. The client's hemodynamic instability and hypoxemia are life-threatening and must be addressed first.",
        "mnemonic": "PANCREAS (Causes of Pancreatitis):\nP - Post-ERCP\nA - Alcohol\nN - Neoplasm\nC - Cholelithiasis (gallstones)\nR - Rx (Drugs: diuretics, steroids)\nE - ERCP\nA - Autoimmune\nS - Scorpion sting / Surgery / Trauma",
        "reviewUnits": [
            "Gastrointestinal Disorders: Acute Pancreatitis",
            "Fluid and Electrolyte Imbalances",
            "Shock: Hypovolemic",
            "Gas Exchange: Acute Respiratory Distress Syndrome (ARDS)",
            "Prioritization of Care"
        ]
    },
    "scoring": {
        "method": "+/-",
        "maxPoints": 5
    },
    "pedagogy": {
        "bloomLevel": "Apply",
        "cjmmStep": "Take Action",
        "nclexCategory": "Physiological Integrity"
    },
    "correctOptionId": "option1",
    "qualityMark": "NGN-2026-HI-FI",
    "healedAt": "2026-02-28T18:30:05.774Z"
}