{
    "id": "New-v26-1772080246645-3003",
    "stem": "Based on the patient's presentation and lab results, the most likely diagnosis is sepsis secondary to a suspected urinary tract infection (UTI). The priority intervention is to administer [FILL IN THE BLANK] and obtain blood cultures.",
    "type": "clozeDropdown",
    "options": [
        {
            "id": "a",
            "text": "broad-spectrum antibiotics"
        },
        {
            "id": "b",
            "text": "antipyretics"
        },
        {
            "id": "c",
            "text": "analgesics"
        },
        {
            "id": "d",
            "text": "oxygen therapy"
        }
    ],
    "scoring": {
        "method": "allOrNothing",
        "maxPoints": 1
    },
    "pedagogy": {
        "cjmmStep": "analyzeCues",
        "topicTags": [
            "Sepsis",
            "Urinary Tract Infection",
            "Infection Control",
            "Pharmacology"
        ],
        "bloomLevel": "apply",
        "difficulty": 3,
        "nclexCategory": "Physiological Adaptation"
    },
    "rationale": {
        "correct": "Broad-spectrum antibiotics are crucial in treating sepsis, targeting the likely source of infection before definitive cultures are available. Delaying antibiotic administration in sepsis significantly increases mortality. Rapid initiation of antibiotics is a cornerstone of sepsis management, aiming to control the infection and prevent further systemic damage. The choice of antibiotic should be guided by local resistance patterns and the suspected source of infection.",
        "mnemonic": {
            "SEPSIS": "Seek source, Evaluate, Prevent spread, Support circulation, Improve oxygen, Send cultures, Start antibiotics"
        },
        "incorrect": "Antipyretics alone will not address the underlying infection causing the sepsis. While important for comfort and reducing fever, they are not a priority intervention in the initial management of sepsis. Addressing the infection is paramount to preventing further deterioration.",
        "questionTrap": {
            "trap1": "Focus on addressing the infection FIRST, then pain and fever management. While comfort measures are important, they are secondary to controlling the source of sepsis."
        },
        "clinicalPearls": [
            "The Surviving Sepsis Campaign recommends administering broad-spectrum antibiotics within one hour of sepsis recognition to improve patient outcomes.",
            "Blood cultures should always be obtained prior to antibiotic administration, if possible, without delaying antibiotic therapy. This helps identify the causative organism and guide antibiotic selection.",
            "Monitor the patient closely for signs of improvement or deterioration after antibiotic administration. Adjust the antibiotic regimen based on culture results and the patient's clinical response."
        ]
    },
    "itemContext": {
        "sbar": "S: 78-year-old female admitted at 14:30 with altered mental status and fever. R: Patient reports burning with urination for 3 days. History of hypertension and type 2 diabetes. A: Vital signs: Temp 38.9°C, HR 110 bpm, RR 24, BP 90/60 mmHg, SpO2 92% on room air. Labs show elevated WBC and lactate. Urine analysis pending. Suspect sepsis secondary to UTI. B: Administer broad-spectrum antibiotics and obtain blood cultures STAT. Monitor vital signs closely. Consider fluid resuscitation.",
        "tabs": [
            {
                "id": "sbar",
                "title": "SBAR",
                "content": "S: 78-year-old female admitted at 14:30 with altered mental status and fever. R: Patient reports burning with urination for 3 days. History of hypertension and type 2 diabetes. A: Vital signs: Temp 38.9°C, HR 110 bpm, RR 24, BP 90/60 mmHg, SpO2 92% on room air. Labs show elevated WBC and lactate. Urine analysis pending. Suspect sepsis secondary to UTI. B: Administer broad-spectrum antibiotics and obtain blood cultures STAT. Monitor vital signs closely. Consider fluid resuscitation."
            },
            {
                "id": "vitals",
                "title": "Vitals",
                "content": "<table><thead><tr><th>Vital Sign</th><th>Value</th></tr></thead><tbody><tr><td>Temperature</td><td>38.9°C</td></tr><tr><td>Heart Rate</td><td>110 bpm</td></tr><tr><td>Respiratory Rate</td><td>24</td></tr><tr><td>Blood Pressure</td><td>90/60 mmHg</td></tr><tr><td>SpO2</td><td>92% on room air</td></tr></tbody></table>"
            },
            {
                "id": "labs",
                "title": "Labs",
                "content": "<table><thead><tr><th>Lab</th><th>Value</th><th>Reference Range</th></tr></thead><tbody><tr><td>WBC</td><td>18,000/μL</td><td>4,500-11,000/μL</td></tr><tr><td>Lactate</td><td>4.0 mmol/L</td><td>0.5-2.2 mmol/L</td></tr><tr><td>Urine Analysis</td><td>Pending</td><td></td></tr></tbody></table>"
            },
            {
                "id": "radiology",
                "title": "Radiology",
                "content": "No radiology reports available."
            },
            {
                "id": "mar",
                "title": "MAR",
                "content": "Patient is allergic to Penicillin. No current medications ordered."
            }
        ],
        "patient": {
            "age": 78,
            "gender": "Female",
            "allergies": [
                "Penicillin"
            ],
            "medicalHistory": [
                "Hypertension",
                "Type 2 Diabetes"
            ]
        }
    },
    "correctAnswer": "broad-spectrum antibiotics",
    "sentinelStatus": "deep_healed_v2026"
}