{
    "id": "pheochromocytoma_signs_clozeDropdown_v1",
    "type": "clozeDropdown",
    "stem": "Complete the assessment logic for a client with a suspected adrenal medulla tumor.",
    "template": "The client with pheochromocytoma typically experiences episodic {{hypertension}}. The nurse should strictly avoid {{palpation}} during the assessment of this client.",
    "blanks": [
        {
            "id": "hypertension",
            "options": [
                "pounding headaches and tachycardia",
                "bradycardia and hypotension",
                "weight gain and lethargy"
            ],
            "correctOption": "pounding headaches and tachycardia"
        },
        {
            "id": "palpation",
            "options": [
                "abdominal palpation",
                "checking peripheral pulses",
                "percussion of the chest"
            ],
            "correctOption": "abdominal palpation"
        }
    ],
    "pedagogy": {
        "bloomLevel": "analyze",
        "cjmmStep": "recognizeCues",
        "nclexCategory": "Physiological Adaptation",
        "difficulty": 4,
        "topicTags": [
            "Endocrine",
            "Safety",
            "Assessment"
        ]
    },
    "rationale": {
        "correct": "Pheochromocytoma releases massive amounts of catecholamines (Epinephrine/Norepinephrine). This causes catastrophic hypertension. Abdominal palpation can trigger the release of these hormones from the tumor, potentially causing a stroke or MI.",
        "incorrect": "The symptoms are the opposite of lethargy. Peripheral pulses are safe to check.",
        "answerBreakdown": [
            {
                "label": "Blank 1",
                "content": "The selection of \"pounding headaches and tachycardia\" correctly completes the clinical hypothesis based on assessment cues.",
                "isCorrect": true
            },
            {
                "label": "Blank 2",
                "content": "The selection of \"abdominal palpation\" correctly completes the clinical hypothesis based on assessment cues.",
                "isCorrect": true
            }
        ],
        "clinicalPearls": [
            "Diagnosis often involves a 24-hour urine collection for VMA (vanillylmandelic acid) and metanephrines."
        ],
        "questionTrap": {
            "trap": "The 'No Touch' Rule",
            "howToOvercome": "Remember 'Pheo = Pounding' and 'No Palpating'. Similar to Wilms' tumor in children, if you touch the lump, you release the poison."
        },
        "mnemonic": {
            "title": "5 P's",
            "expansion": "Pressure (High), Palpitations, Perspiration, Pain (Headache), Pallor."
        },
        "reviewUnits": [
            {
                "heading": "Diseases of the Adrenal Medulla",
                "body": "Nurses monitor for hypertensive crisis. Alpha-blockers (Doxazosin) are given *before* beta-blockers to prevent unopposed alpha-stimulation.",
                "source": "Medical-Surgical Nursing: Adrenal Tumors"
            }
        ]
    },
    "scoring": {
        "method": "polytomous",
        "maxPoints": 2
    }
}