{
    "id": "highlight_stroke_acute_sample_v2026",
    "type": "highlight",
    "stem": "Click to highlight the findings that are most likely associated with the client's current neurologic event.",
    "passage": "A [72-year-old female] is evaluated in the Emergency Department for [sudden onset of left-sided weakness] and [slurred speech] that began 45 minutes ago. The nurse notes [facial drooping on the left side] and a [BP of 192/104 mmHg]. The client appears [anxious but cooperative].",
    "correctSpans": [
        "sudden onset of left-sided weakness",
        "slurred speech",
        "facial drooping on the left side"
    ],
    "itemContext": {
        "tabs": [
            {
                "id": "sbar",
                "title": "Nurses' Notes",
                "content": "S: 72/F brought by EMS for acute neurologic changes.\nB: History of hypertension and atrial fibrillation. Non-compliant with apixaban.\nA: Sudden onset left-sided hemiparesis. GCS 14 (E4, V4, M6).\nR: Initiate stroke protocol and prepare for CT head."
            },
            {
                "id": "vitals",
                "title": "Vital Signs",
                "content": "Time: 14:00 | BP: 192/104 | HR: 98 (irregular) | RR: 18 | SpO2: 95% on RA"
            }
        ]
    },
    "pedagogy": {
        "bloomLevel": "analyze",
        "cjmmStep": "recognizeCues",
        "nclexCategory": "Physiological Adaptation",
        "difficulty": 4,
        "topicTags": [
            "Stroke"
        ]
    },
    "rationale": {
        "correct": "Sudden onset focal neurologic deficits (weakness, speech, facial droop) are hallmark signs of acute ischemic stroke.",
        "answerBreakdown": [
            {
                "label": "sudden onset of left-sided weakness",
                "content": "Classical presentation of stroke affecting the right hemisphere.",
                "isCorrect": true
            }
        ],
        "clinicalPearls": [
            "Time is Brain: Rapid recognition is key for tPA eligibility."
        ],
        "questionTrap": {
            "trap": "Highlighting hypertension as a sign of stroke.",
            "howToOvercome": "Hypertension is a risk factor or compensation, not always a clinical sign of the stroke itself in the same way focal deficits are."
        },
        "mnemonic": {
            "title": "B.E. F.A.S.T.",
            "expansion": "Balance, Eyes, Face, Arms, Speech, Time"
        }
    },
    "scoring": {
        "method": "polytomous",
        "maxPoints": 3
    },
    "sentinelStatus": "healed_v2026_v9"
}